Metadata-Version: 1.0
Name: udsxmlrpc
Version: 0.1.6
Summary: Unix domain socket XML-RPC
Home-page: https://github.com/daizhaolin/udsxmlrpc
Author: daizhaolin
Author-email: UNKNOWN
License: BSD
Platform: 
